[
  {
    "title": "Jo. Brown"
  },
  {
    "title": "T.Choice"
  },
  {
    "title": "J.Malone"
  },
  {
    "title": "Jz. Rodgers"
  },
  {
    "title": "M.Gordon"
  },
  {
    "title": "K.Farrow"
  },
  {
    "title": "R.Turbin"
  },
  {
    "title": "M.King"
  },
  {
    "title": "D.Chark"
  },
  {
    "title": "B.Saine"
  },
  {
    "title": "H.Valles"
  },
  {
    "title": "R.Burkhead"
  },
  {
    "title": "S.Coley"
  },
  {
    "title": "Z.Strief"
  },
  {
    "title": "K.Small"
  },
  {
    "title": "C.Ford"
  },
  {
    "title": "K.Curtis"
  },
  {
    "title": "J.Locke"
  },
  {
    "title": "M.Bradley"
  },
  {
    "title": "B.Brohm"
  },
  {
    "title": "M.Roberts"
  },
  {
    "title": "J.Mastrud"
  },
  {
    "title": "A.Fasano"
  },
  {
    "title": "C.Pennington"
  },
  {
    "title": "S.Culkin"
  },
  {
    "title": "M.Reece"
  },
  {
    "title": "J.Hemingway"
  },
  {
    "title": "H.Nicks"
  },
  {
    "title": "L.Willson"
  },
  {
    "title": "R.Gathers"
  },
  {
    "title": "T.Green"
  },
  {
    "title": "S.Larsen"
  },
  {
    "title": "R.Tonyan"
  },
  {
    "title": "J.Doyle"
  },
  {
    "title": "A.McCarron"
  },
  {
    "title": "G.Davis"
  },
  {
    "title": "T.Copper"
  },
  {
    "title": "Z.Sudfeld"
  },
  {
    "title": "B.Braunecker"
  },
  {
    "title": "K.Williams"
  },
  {
    "title": "M.Spaeth"
  },
  {
    "title": "Z.Potter"
  },
  {
    "title": "S.Roberts"
  },
  {
    "title": "T.Quinn"
  },
  {
    "title": "T.Cohen"
  },
  {
    "title": "D.Briscoe"
  },
  {
    "title": "S.Logan"
  },
  {
    "title": "D.Reaves"
  },
  {
    "title": "C.Walford"
  },
  {
    "title": "D.Rhodes"
  },
  {
    "title": "S.Morey"
  },
  {
    "title": "N.Roosevelt"
  },
  {
    "title": "N.Toon"
  },
  {
    "title": "C.Moore"
  },
  {
    "title": "R.Herron"
  },
  {
    "title": "C.Beathard"
  },
  {
    "title": "V.Davis"
  },
  {
    "title": "N.Vannett"
  },
  {
    "title": "J.Heath"
  },
  {
    "title": "A.Battle"
  },
  {
    "title": "M.Tauscher"
  },
  {
    "title": "T.Mason"
  },
  {
    "title": "R.Grossman"
  },
  {
    "title": "Jo.Anderson"
  },
  {
    "title": "R.Mallett"
  },
  {
    "title": "M.Easley"
  },
  {
    "title": "J.Tolliver"
  },
  {
    "title": "A.Levine"
  },
  {
    "title": "K.Martin"
  },
  {
    "title": "D.Gettis"
  },
  {
    "title": "C.Edmonds"
  },
  {
    "title": "K.Boller"
  },
  {
    "title": "T.Clemons"
  },
  {
    "title": "M.Gillislee"
  },
  {
    "title": "M.Jenkins"
  },
  {
    "title": "T.Palko"
  },
  {
    "title": "J.Norwood"
  },
  {
    "title": "N.Miller"
  },
  {
    "title": "G.Bernard"
  },
  {
    "title": "J.Bush"
  },
  {
    "title": "A.Castonzo"
  },
  {
    "title": "B.Anger"
  },
  {
    "title": "J.Croom"
  },
  {
    "title": "L.Byrd"
  },
  {
    "title": "J.White"
  },
  {
    "title": "A.Davis"
  },
  {
    "title": "T.Patrick"
  },
  {
    "title": "T.Pryor"
  },
  {
    "title": "M.Trubisky"
  },
  {
    "title": "B.Wilson"
  },
  {
    "title": "M.Mariota"
  },
  {
    "title": "M.Scifres"
  },
  {
    "title": "E.Tomlinson"
  },
  {
    "title": "R.McMichael"
  },
  {
    "title": "J.Washington"
  },
  {
    "title": "K.Meier"
  },
  {
    "title": "R.Goodman"
  },
  {
    "title": "J.Abbrederis"
  },
  {
    "title": "M.McNutt"
  },
  {
    "title": "A.Ellis"
  },
  {
    "title": "J.Foschi"
  },
  {
    "title": "S.Heiden"
  },
  {
    "title": "E.Royal"
  },
  {
    "title": "W.Snead"
  },
  {
    "title": "K.Barner"
  },
  {
    "title": "D.Stanton"
  },
  {
    "title": "D.Goldson"
  },
  {
    "title": "Z.Beadles"
  },
  {
    "title": "G.Jones"
  },
  {
    "title": "M.Glennon"
  },
  {
    "title": "A.Abdullah"
  },
  {
    "title": "G.Jackson"
  },
  {
    "title": "D.Njoku"
  },
  {
    "title": "K.Elliott"
  },
  {
    "title": "K.Lumpkin"
  },
  {
    "title": "B.Ewing"
  },
  {
    "title": "S.Vallos"
  },
  {
    "title": "J.Cooper"
  },
  {
    "title": "L.Jackson"
  },
  {
    "title": "E.Wilford"
  },
  {
    "title": "D.Garrard"
  },
  {
    "title": "B.Mihalik"
  },
  {
    "title": "J.Best"
  },
  {
    "title": "J.Olawale"
  },
  {
    "title": "D.Dawkins"
  },
  {
    "title": "A.Humphries"
  },
  {
    "title": "T.Logan"
  },
  {
    "title": "M.Gaines"
  },
  {
    "title": "Ty.Williams"
  },
  {
    "title": "D.Allen"
  },
  {
    "title": "R.Wilson"
  },
  {
    "title": "K.Adams"
  },
  {
    "title": "D.Wilson"
  },
  {
    "title": "A.Blue"
  },
  {
    "title": "L.Louis"
  },
  {
    "title": "L.Stephens-Howling"
  },
  {
    "title": "B.Harris"
  },
  {
    "title": "P.Harvin"
  },
  {
    "title": "C.McIntyre"
  },
  {
    "title": "J.Franks"
  },
  {
    "title": "D.Scott"
  },
  {
    "title": "F.Jones"
  },
  {
    "title": "G.Robinson"
  },
  {
    "title": "R.Lindell"
  },
  {
    "title": "E.Weems"
  },
  {
    "title": "J.Herndon"
  },
  {
    "title": "S.Ware"
  },
  {
    "title": "M.Manningham"
  },
  {
    "title": "J.Baker"
  },
  {
    "title": "P.Mahomes"
  },
  {
    "title": "B.Sankey"
  },
  {
    "title": "M.Flynn"
  },
  {
    "title": "J.Adams"
  },
  {
    "title": "M.Kelly"
  },
  {
    "title": "J.Nelson"
  },
  {
    "title": "G.Wilson"
  },
  {
    "title": "Jaron.Brown"
  },
  {
    "title": "T.Castille"
  },
  {
    "title": "C.Maragos"
  },
  {
    "title": "J.Whitehead"
  },
  {
    "title": "D.Tialavea"
  },
  {
    "title": "G.Graham"
  },
  {
    "title": "A.Wilson"
  },
  {
    "title": "E.Graham"
  },
  {
    "title": "J.Saunders"
  },
  {
    "title": "Ry.Mathews"
  },
  {
    "title": "S.Hurd"
  },
  {
    "title": "J.Delhomme"
  },
  {
    "title": "M.Leinart"
  },
  {
    "title": "B.Zylstra"
  },
  {
    "title": "B.Schwenke"
  },
  {
    "title": "A.Caldwell"
  },
  {
    "title": "D.Aromashodu"
  },
  {
    "title": "R.Gage"
  },
  {
    "title": "T.Savage"
  },
  {
    "title": "B.Watson"
  },
  {
    "title": "A.Rodgers"
  },
  {
    "title": "C.Clemons"
  },
  {
    "title": "C.Cochart"
  },
  {
    "title": "M.Gesicki"
  },
  {
    "title": "A.Cleveland"
  },
  {
    "title": "DanielThomas"
  },
  {
    "title": "A.Feeley"
  },
  {
    "title": "W.Snead IV"
  },
  {
    "title": "B.Finneran"
  },
  {
    "title": "C.Kaepernick"
  },
  {
    "title": "A.Becht"
  },
  {
    "title": "A.Binns"
  },
  {
    "title": "J.Callahan"
  },
  {
    "title": "J.Kelly"
  },
  {
    "title": "K.Null"
  },
  {
    "title": "Shaun.Hill"
  },
  {
    "title": "T.Moeaki"
  },
  {
    "title": "F.Toussaint"
  },
  {
    "title": "D.Fluellen"
  },
  {
    "title": "T.Brandstater"
  },
  {
    "title": "De.Thomas"
  },
  {
    "title": "L.Lawton"
  },
  {
    "title": "R.Nix"
  },
  {
    "title": "S.Bradford"
  },
  {
    "title": "B.Cunningham"
  },
  {
    "title": "M.Kemp"
  },
  {
    "title": "J.Peelle"
  },
  {
    "title": "K.Reuland"
  },
  {
    "title": "D.Sproles"
  },
  {
    "title": "C.Shorts III"
  },
  {
    "title": "D.Orlovsky"
  },
  {
    "title": "Ju.Jones"
  },
  {
    "title": "E.Doucet"
  },
  {
    "title": "S.Renfree"
  },
  {
    "title": "J.Owens"
  },
  {
    "title": "B.Volek"
  },
  {
    "title": "L.Naanee"
  },
  {
    "title": "M.Preston"
  },
  {
    "title": "D.Driver"
  },
  {
    "title": "C.Simms"
  },
  {
    "title": "E.Bennett"
  },
  {
    "title": "B.Bostick"
  },
  {
    "title": "M.Caussin"
  },
  {
    "title": "T.Hilton"
  },
  {
    "title": "D.Anderson"
  },
  {
    "title": "M.Ateman"
  },
  {
    "title": "B.Bolden"
  },
  {
    "title": "T.Decker"
  },
  {
    "title": "T.Brady"
  },
  {
    "title": "K.Hogan"
  },
  {
    "title": "C.Kessler"
  },
  {
    "title": "C.Redman"
  },
  {
    "title": "L.White"
  },
  {
    "title": "G.Winston"
  },
  {
    "title": "H.Nakamura"
  },
  {
    "title": "S.Smith"
  },
  {
    "title": "D.Fletcher"
  },
  {
    "title": "L.Edwards"
  },
  {
    "title": "B.McManus"
  },
  {
    "title": "K.Lee"
  },
  {
    "title": "D.Davis"
  },
  {
    "title": "B.Smelley"
  },
  {
    "title": "S.Ajirotutu"
  },
  {
    "title": "K.Washington"
  },
  {
    "title": "Be.Scott"
  },
  {
    "title": "K.Hunter"
  },
  {
    "title": "M.Bryant"
  },
  {
    "title": "C.Pressley"
  },
  {
    "title": "J.O'Shaughnessy"
  },
  {
    "title": "J.Lewis"
  },
  {
    "title": "T.Clayton"
  },
  {
    "title": "J.Kleinsasser"
  },
  {
    "title": "J.Natson"
  },
  {
    "title": "J.Hastings"
  },
  {
    "title": "H.Hurst"
  },
  {
    "title": "J.Richard"
  },
  {
    "title": "C.Hyde"
  },
  {
    "title": "A.Lee"
  },
  {
    "title": "J.Butt"
  },
  {
    "title": "W.Tye"
  },
  {
    "title": "A.Harris"
  },
  {
    "title": "J.Standeford"
  },
  {
    "title": "A.Williams"
  },
  {
    "title": "R.Quinn"
  },
  {
    "title": "T.Gurley"
  },
  {
    "title": "L.Pinkard"
  },
  {
    "title": "C.Steltz"
  },
  {
    "title": "P.Hillis"
  },
  {
    "title": "J.McKinnon"
  },
  {
    "title": "T.Ginn"
  },
  {
    "title": "L.Bell"
  },
  {
    "title": "B.Robiskie"
  },
  {
    "title": "D.Mays"
  },
  {
    "title": "S.Wallace"
  },
  {
    "title": "S.Dawson"
  },
  {
    "title": "N.Hines"
  },
  {
    "title": "M.Bundy"
  },
  {
    "title": "G.Mills"
  },
  {
    "title": "T.Riddick"
  },
  {
    "title": "M.Gibson"
  },
  {
    "title": "D.Zeigler"
  },
  {
    "title": "I.Smith"
  },
  {
    "title": "P.Hubbard"
  },
  {
    "title": "J.Dreessen"
  },
  {
    "title": "R.Malleck"
  },
  {
    "title": "C.Portis"
  },
  {
    "title": "T.Crabtree"
  },
  {
    "title": "R.Bush"
  },
  {
    "title": "J.Crowder"
  },
  {
    "title": "B.Gradkowski"
  },
  {
    "title": "L.Kendricks"
  },
  {
    "title": "C.Stuckey"
  },
  {
    "title": "J.Reed"
  },
  {
    "title": "M.McGlynn"
  },
  {
    "title": "J.Jackson"
  },
  {
    "title": "S.Tolzien"
  },
  {
    "title": "J.Gage"
  },
  {
    "title": "C.Carter"
  },
  {
    "title": "J.Cunningham"
  },
  {
    "title": "A.Roberts"
  },
  {
    "title": "B.Wade"
  },
  {
    "title": "S.Havner"
  },
  {
    "title": "R.Richardson"
  },
  {
    "title": "M.McBriar"
  },
  {
    "title": "D.Sepulveda"
  },
  {
    "title": "A.Hill"
  },
  {
    "title": "A.Cooper"
  },
  {
    "title": "Q.Dunbar"
  },
  {
    "title": "E.Rogers"
  },
  {
    "title": "D.Young"
  },
  {
    "title": "T.Cadet"
  },
  {
    "title": "C.Meredith"
  },
  {
    "title": "N.Burleson"
  },
  {
    "title": "J.Demps"
  },
  {
    "title": "B.Engram"
  },
  {
    "title": "A.Collie"
  },
  {
    "title": "L.Coles"
  },
  {
    "title": "T.Tebow"
  },
  {
    "title": "D.Parker"
  },
  {
    "title": "B.Tyms"
  },
  {
    "title": "B.Pettigrew"
  },
  {
    "title": "M.McNeill"
  },
  {
    "title": "N.Sudfeld"
  },
  {
    "title": "J.Brown"
  },
  {
    "title": "W.Lutz"
  },
  {
    "title": "M.Otto"
  },
  {
    "title": "M.Asiata"
  },
  {
    "title": "T.Grisham"
  },
  {
    "title": "T.Carter"
  },
  {
    "title": "A.Firkser"
  },
  {
    "title": "M.Pouncey"
  },
  {
    "title": "J.Dugan"
  },
  {
    "title": "K.Cole"
  },
  {
    "title": "K.Gaskins"
  },
  {
    "title": "M.Gallup"
  },
  {
    "title": "D.Robinson"
  },
  {
    "title": "C.Daniel"
  },
  {
    "title": "M.Koenen"
  },
  {
    "title": "C.Dahl"
  },
  {
    "title": "T.Hill"
  },
  {
    "title": "J.Wilkins"
  },
  {
    "title": "H.Krieger Coble"
  },
  {
    "title": "R.Griffin"
  },
  {
    "title": "R.Travis"
  },
  {
    "title": "S.Moss"
  },
  {
    "title": "B.White"
  },
  {
    "title": "K.Hodge"
  },
  {
    "title": "D.Sanzenbacher"
  },
  {
    "title": "Dam. Williams"
  },
  {
    "title": "R.Agnew"
  },
  {
    "title": "M.Colston"
  },
  {
    "title": "G.Farmer"
  },
  {
    "title": "J.Staley"
  },
  {
    "title": "R.McLeod"
  },
  {
    "title": "G.Little"
  },
  {
    "title": "Z.Pianalto"
  },
  {
    "title": "W.McGahee"
  },
  {
    "title": "A.Auclair"
  },
  {
    "title": "R.Torain"
  },
  {
    "title": "M.Hoomanawanui"
  },
  {
    "title": "J.Hester"
  },
  {
    "title": "A.Bryant"
  },
  {
    "title": "E.Dickson"
  },
  {
    "title": "W.Fuller V"
  },
  {
    "title": "P.Dawson"
  },
  {
    "title": "G.Johnson"
  },
  {
    "title": "T.Sherfield"
  },
  {
    "title": "P.Barber"
  },
  {
    "title": "B.Leftwich"
  },
  {
    "title": "M.Hazel"
  },
  {
    "title": "B.Swain"
  },
  {
    "title": "K.Orton"
  },
  {
    "title": "C.Shorts"
  },
  {
    "title": "B.Nortman"
  },
  {
    "title": "T.Romo"
  },
  {
    "title": "J.Blackmon"
  },
  {
    "title": "D.Gronkowski"
  },
  {
    "title": "T.Williams"
  },
  {
    "title": "D.Schouman"
  },
  {
    "title": "K.Eckel"
  },
  {
    "title": "C.Erving"
  },
  {
    "title": "M.Bulger"
  },
  {
    "title": "J.Sprinkle"
  },
  {
    "title": "M.Jensen"
  },
  {
    "title": "J.Langford"
  },
  {
    "title": "B.Golden"
  },
  {
    "title": "R.Dwelley"
  },
  {
    "title": "L.Donnell"
  },
  {
    "title": "N.Vasher"
  },
  {
    "title": "B.Osweiler"
  },
  {
    "title": "L.Brazill"
  },
  {
    "title": "Ar.Smith"
  },
  {
    "title": "D.Fells"
  },
  {
    "title": "A.Brown"
  },
  {
    "title": "M.Campbell"
  },
  {
    "title": "M.Barber"
  },
  {
    "title": "J.Forsett"
  },
  {
    "title": "M.Bell"
  },
  {
    "title": "J.Witten"
  },
  {
    "title": "M.Hasselbeck"
  },
  {
    "title": "J.Crockett"
  },
  {
    "title": "A.Stewart"
  },
  {
    "title": "D.Hester"
  },
  {
    "title": "D.Ratley"
  },
  {
    "title": "T.Gabriel"
  },
  {
    "title": "J.Lane"
  },
  {
    "title": "D.Herron"
  },
  {
    "title": "C.Wentz"
  },
  {
    "title": "M.Jones Jr."
  },
  {
    "title": "C.Beebe"
  },
  {
    "title": "J.Strong"
  },
  {
    "title": "J.Gray"
  },
  {
    "title": "J.Manziel"
  },
  {
    "title": "J.Stoneburner"
  },
  {
    "title": "B.Clark"
  },
  {
    "title": "C.Johnson"
  },
  {
    "title": "J.Jernigan"
  },
  {
    "title": "B.Hundley"
  },
  {
    "title": "B.Hoover"
  },
  {
    "title": "I.Sopoaga"
  },
  {
    "title": "T.Holt"
  },
  {
    "title": "S.Perry"
  },
  {
    "title": "G.Barnidge"
  },
  {
    "title": "J.Feely"
  },
  {
    "title": "W.Allen"
  },
  {
    "title": "R.Williams"
  },
  {
    "title": "S.Shepard"
  },
  {
    "title": "J.Locker"
  },
  {
    "title": "R.Cooper"
  },
  {
    "title": "J.Caulcrick"
  },
  {
    "title": "A.Robinson"
  },
  {
    "title": "B.Askew"
  },
  {
    "title": "D.Woodhead"
  },
  {
    "title": "F.Hammond"
  },
  {
    "title": "L.Treadwell"
  },
  {
    "title": "J.Huff"
  },
  {
    "title": "M.Crosby"
  },
  {
    "title": "M.Crabtree"
  },
  {
    "title": "D.Turner"
  },
  {
    "title": "J.Gresham"
  },
  {
    "title": "D.Henderson"
  },
  {
    "title": "R.Hochstein"
  },
  {
    "title": "M.Williams"
  },
  {
    "title": "L.Cooke"
  },
  {
    "title": "R.Rice"
  },
  {
    "title": "D.Henry"
  },
  {
    "title": "T.Masthay"
  },
  {
    "title": "R.Spadola"
  },
  {
    "title": "A.Gonzalez"
  },
  {
    "title": "C.Hikutini"
  },
  {
    "title": "B.Gabbert"
  },
  {
    "title": "N.Harris"
  },
  {
    "title": "M.Shuler"
  },
  {
    "title": "B.Reedy"
  },
  {
    "title": "C.Jennings"
  },
  {
    "title": "C.Ochocinco"
  },
  {
    "title": "R.Grant"
  },
  {
    "title": "C.Mooney"
  },
  {
    "title": "T.Williamson"
  },
  {
    "title": "J.Holton"
  },
  {
    "title": "I.Redman"
  },
  {
    "title": "S.Hauschka"
  },
  {
    "title": "B.Bortles"
  },
  {
    "title": "Dn. Thomas"
  },
  {
    "title": "A.Tanney"
  },
  {
    "title": "T.Edmunds"
  },
  {
    "title": "N.O'Leary"
  },
  {
    "title": "T.Bouman"
  },
  {
    "title": "M.Sims-Walker"
  },
  {
    "title": "L.Pope"
  },
  {
    "title": "A.Young"
  },
  {
    "title": "C.Peerman"
  },
  {
    "title": "J.Beck"
  },
  {
    "title": "E.Engram"
  },
  {
    "title": "W.Powell"
  },
  {
    "title": "D.Booker"
  },
  {
    "title": "S.Watkins"
  },
  {
    "title": "P.White"
  },
  {
    "title": "E.Moore"
  },
  {
    "title": "M.Dodge"
  },
  {
    "title": "R.Mundy"
  },
  {
    "title": "T.Gerhart"
  },
  {
    "title": "S.Jackson"
  },
  {
    "title": "J.Gilmore"
  },
  {
    "title": "J.Palmer"
  },
  {
    "title": "R.Freeman"
  },
  {
    "title": "C.Clay"
  },
  {
    "title": "Z.Mettenberger"
  },
  {
    "title": "E.Lorig"
  },
  {
    "title": "T.Benjamin"
  },
  {
    "title": "W.Ta'ufo'ou"
  },
  {
    "title": "B.Cooks"
  },
  {
    "title": "J.Berry"
  },
  {
    "title": "J.Dillard"
  },
  {
    "title": "S.Barkley"
  },
  {
    "title": "D.Amendola"
  },
  {
    "title": "P.Parker"
  },
  {
    "title": "S.Williams"
  },
  {
    "title": "C.Hall"
  },
  {
    "title": "N.Williams"
  },
  {
    "title": "Mik.Williams"
  },
  {
    "title": "Ja.Jones"
  },
  {
    "title": "J.Avant"
  },
  {
    "title": "M.Haack"
  },
  {
    "title": "J.Moore"
  },
  {
    "title": "F.Taylor"
  },
  {
    "title": "M.Rucker"
  },
  {
    "title": "N.Eachus"
  },
  {
    "title": "A.Cross"
  },
  {
    "title": "R.Tannehill"
  },
  {
    "title": "A.Hicks"
  },
  {
    "title": "D.Cobb"
  },
  {
    "title": "B.Westbrook"
  },
  {
    "title": "C.Kupp"
  },
  {
    "title": "M.Jones-Drew"
  },
  {
    "title": "T.Rudolph"
  },
  {
    "title": "J.Vaughan"
  },
  {
    "title": "J.Poyer"
  },
  {
    "title": "H.Hynoski"
  },
  {
    "title": "Al.Smith"
  },
  {
    "title": "S.Chandler"
  },
  {
    "title": "A.Smith"
  },
  {
    "title": "J.Snelling"
  },
  {
    "title": "C.Woodson"
  },
  {
    "title": "R.Seals-Jones"
  },
  {
    "title": "K.Lamm"
  },
  {
    "title": "B.Jones"
  },
  {
    "title": "C.Reynolds"
  },
  {
    "title": "G.Sanborn"
  },
  {
    "title": "A.Podlesh"
  },
  {
    "title": "M.Campanaro"
  },
  {
    "title": "L.Booker"
  },
  {
    "title": "R.Barden"
  },
  {
    "title": "B.Fields"
  },
  {
    "title": "J.Watson"
  },
  {
    "title": "T.Montgomery"
  },
  {
    "title": "W.Johnson"
  },
  {
    "title": "J.Galloway"
  },
  {
    "title": "B.St. Pierre"
  },
  {
    "title": "P.Lasike"
  },
  {
    "title": "M.Mulligan"
  },
  {
    "title": "D.White"
  },
  {
    "title": "D.Walker"
  },
  {
    "title": "B.Petty"
  },
  {
    "title": "S.Redd"
  },
  {
    "title": "P.Lynch"
  },
  {
    "title": "C.Harbor"
  },
  {
    "title": "R.Brockel"
  },
  {
    "title": "J.Perillo"
  },
  {
    "title": "J.Mixon"
  },
  {
    "title": "A.Shaheen"
  },
  {
    "title": "J.Heuerman"
  },
  {
    "title": "M.Cox"
  },
  {
    "title": "Y.Figurs"
  },
  {
    "title": "D.Smythe"
  },
  {
    "title": "T.Richardson"
  },
  {
    "title": "S.Darnold"
  },
  {
    "title": "K.Pearson"
  },
  {
    "title": "D.Johnson Jr."
  },
  {
    "title": "A.Janovich"
  },
  {
    "title": "C.Givens"
  },
  {
    "title": "H.Henry"
  },
  {
    "title": "B.Roethlisberger"
  },
  {
    "title": "C.Artis-Payne"
  },
  {
    "title": "K.Clay"
  },
  {
    "title": "J.Stevens"
  },
  {
    "title": "DJ.Davis"
  },
  {
    "title": "M.Barkley"
  },
  {
    "title": "M.Valdes-Scantling"
  },
  {
    "title": "M.Gray"
  },
  {
    "title": "T.Lockett"
  },
  {
    "title": "A.Bradshaw"
  },
  {
    "title": "T.Owens"
  },
  {
    "title": "J.Graham"
  },
  {
    "title": "D.Vitale"
  },
  {
    "title": "D.Dinkins"
  },
  {
    "title": "D.Sims"
  },
  {
    "title": "H.Sharp"
  },
  {
    "title": "Dan.Thomas"
  },
  {
    "title": "S.Jones"
  },
  {
    "title": "L.Tomlinson"
  },
  {
    "title": "J.Cumberland"
  },
  {
    "title": "Z.Stacy"
  },
  {
    "title": "M.Alford"
  },
  {
    "title": "G.Escobar"
  },
  {
    "title": "J.Feagles"
  },
  {
    "title": "J.Starks"
  },
  {
    "title": "D.Powe"
  },
  {
    "title": "G.Jennings"
  },
  {
    "title": "M.Clark"
  },
  {
    "title": "A.Green"
  },
  {
    "title": "J.Conner"
  },
  {
    "title": "L.Thomas"
  },
  {
    "title": "L.Betts"
  },
  {
    "title": "T.Graham"
  },
  {
    "title": "M.Gutierrez"
  },
  {
    "title": "C.McCoy"
  },
  {
    "title": "L.Fournette"
  },
  {
    "title": "A.Robinson II"
  },
  {
    "title": "A.Seferian-Jenkins"
  },
  {
    "title": "M.Ball"
  },
  {
    "title": "D.Green-Beckham"
  },
  {
    "title": "R.Jones II"
  },
  {
    "title": "D.Wynn"
  },
  {
    "title": "D.Jennings"
  },
  {
    "title": "Jo.Howard"
  },
  {
    "title": "K.Brent"
  },
  {
    "title": "K.Wilson"
  },
  {
    "title": "A.Dobson"
  },
  {
    "title": "L.Stocker"
  },
  {
    "title": "K.Durham"
  },
  {
    "title": "R.Davis"
  },
  {
    "title": "A.Ekeler"
  },
  {
    "title": "T.Stewart"
  },
  {
    "title": "G.Camarillo"
  },
  {
    "title": "B.Edwards"
  },
  {
    "title": "C.Fiedorowicz"
  },
  {
    "title": "K.Pilares"
  },
  {
    "title": "W.Williams"
  },
  {
    "title": "C.Brate"
  },
  {
    "title": "S.Draughn"
  },
  {
    "title": "N.Solder"
  },
  {
    "title": "K.Rudolph"
  },
  {
    "title": "I.Whitney"
  },
  {
    "title": "J.Boykin"
  },
  {
    "title": "D.Roland"
  },
  {
    "title": "D.Harris"
  },
  {
    "title": "A.Foster"
  },
  {
    "title": "T.Davis"
  },
  {
    "title": "JA.Brown"
  },
  {
    "title": "K.Barnes"
  },
  {
    "title": "M.Boone"
  },
  {
    "title": "S.Richardson"
  },
  {
    "title": "K.Kirkwood"
  },
  {
    "title": "T.Sambrailo"
  },
  {
    "title": "R.Streater"
  },
  {
    "title": "S.Perine"
  },
  {
    "title": "D.Daniels"
  },
  {
    "title": "L.Moore"
  },
  {
    "title": "J.Wright"
  },
  {
    "title": "K.Walter"
  },
  {
    "title": "C.Ham"
  },
  {
    "title": "W.Heller"
  },
  {
    "title": "Z.Miller"
  },
  {
    "title": "J.Addai"
  },
  {
    "title": "D.Bess"
  },
  {
    "title": "R.Cobb"
  },
  {
    "title": "Da.Thomas"
  },
  {
    "title": "R.Gronkowski"
  },
  {
    "title": "J.Hollister"
  },
  {
    "title": "B.Miller"
  },
  {
    "title": "A.Hurns"
  },
  {
    "title": "L.Paulsen"
  },
  {
    "title": "J.Freeman"
  },
  {
    "title": "N.Hughes"
  },
  {
    "title": "J.Klopfenstein"
  },
  {
    "title": "M.Karney"
  },
  {
    "title": "B.Williams"
  },
  {
    "title": "V.Ballard"
  },
  {
    "title": "N.Palmer"
  },
  {
    "title": "B.Celek"
  },
  {
    "title": "T.Ward"
  },
  {
    "title": "M.Ingram"
  },
  {
    "title": "M.Gilyard"
  },
  {
    "title": "O.Darkwa"
  },
  {
    "title": "V.Shiancoe"
  },
  {
    "title": "L.Murray"
  },
  {
    "title": "A.Holmes"
  },
  {
    "title": "M.Morris"
  },
  {
    "title": "P.McAfee"
  },
  {
    "title": "M.Spurlock"
  },
  {
    "title": "P.Peterson"
  },
  {
    "title": "J.Clay"
  },
  {
    "title": "J.Brissett"
  },
  {
    "title": "I.McKenzie"
  },
  {
    "title": "J.O'Sullivan"
  },
  {
    "title": "T.Morstead"
  },
  {
    "title": "R.Ortiz"
  },
  {
    "title": "Z.Jones"
  },
  {
    "title": "M.Massaquoi"
  },
  {
    "title": "K.Robinson"
  },
  {
    "title": "B.Leonard"
  },
  {
    "title": "T.Conklin"
  },
  {
    "title": "J.Amaro"
  },
  {
    "title": "C.Williams"
  },
  {
    "title": "K.Wright"
  },
  {
    "title": "J.Shipley"
  },
  {
    "title": "J.Kearse"
  },
  {
    "title": "V.Young"
  },
  {
    "title": "S.Anderson"
  },
  {
    "title": "C.Uzomah"
  },
  {
    "title": "M.Rivera"
  },
  {
    "title": "E.Amano"
  },
  {
    "title": "M.Andrews"
  },
  {
    "title": "D.Willies"
  },
  {
    "title": "F.Whittaker"
  },
  {
    "title": "B.Green-Ellis"
  },
  {
    "title": "D.Ayers"
  },
  {
    "title": "M.Stovall"
  },
  {
    "title": "R.Greene"
  },
  {
    "title": "J.Losman"
  },
  {
    "title": "C.Latimer"
  },
  {
    "title": "C.Gragg"
  },
  {
    "title": "B.Meester"
  },
  {
    "title": "C.Baker"
  },
  {
    "title": "S.Michel"
  },
  {
    "title": "L.Fitzgerald"
  },
  {
    "title": "W.Dissly"
  },
  {
    "title": "E.James"
  },
  {
    "title": "C.Brown"
  },
  {
    "title": "D.Hamilton"
  },
  {
    "title": "Q.Johnson"
  },
  {
    "title": "T.Murphy"
  },
  {
    "title": "G.McElroy"
  },
  {
    "title": "S.Kelemete"
  },
  {
    "title": "B.Burks"
  },
  {
    "title": "A.Carr"
  },
  {
    "title": "J.James"
  },
  {
    "title": "B.Marquez"
  },
  {
    "title": "V.Green"
  },
  {
    "title": "K.Darby"
  },
  {
    "title": "S.Satele"
  },
  {
    "title": "I.Crowell"
  },
  {
    "title": "C.Davis"
  },
  {
    "title": "D.Grinnage"
  },
  {
    "title": "J.Tamme"
  },
  {
    "title": "D.Kaser"
  },
  {
    "title": "R.Helu"
  },
  {
    "title": "J.Hardee"
  },
  {
    "title": "R.Switzer"
  },
  {
    "title": "M.Brunell"
  },
  {
    "title": "J.Ballard"
  },
  {
    "title": "D.Bryant"
  },
  {
    "title": "D.Dye"
  },
  {
    "title": "R.Parrish"
  },
  {
    "title": "M.Turk"
  },
  {
    "title": "C.Simpson"
  },
  {
    "title": "C.Carson"
  },
  {
    "title": "J.Hunter"
  },
  {
    "title": "N.Washington"
  },
  {
    "title": "G.Allison"
  },
  {
    "title": "J.Stewart"
  },
  {
    "title": "Dr.Davis"
  },
  {
    "title": "C.Owusu"
  },
  {
    "title": "R.Mathews"
  },
  {
    "title": "L.Dunbar"
  },
  {
    "title": "J.Ringer"
  },
  {
    "title": "Del.Walker"
  },
  {
    "title": "T.Washington"
  },
  {
    "title": "J.Reynolds"
  },
  {
    "title": "J.Fowler"
  },
  {
    "title": "M.Burton"
  },
  {
    "title": "V.Brown"
  },
  {
    "title": "A.Erickson"
  },
  {
    "title": "O.Charles"
  },
  {
    "title": "D.Gilreath"
  },
  {
    "title": "J.Tuel"
  },
  {
    "title": "P.Supernaw"
  },
  {
    "title": "J.Samuels"
  },
  {
    "title": "E.Bibbs"
  },
  {
    "title": "D.Morgan"
  },
  {
    "title": "R.Cartwright"
  },
  {
    "title": "M.Forte"
  },
  {
    "title": "M.Egnew"
  },
  {
    "title": "J.Garcia"
  },
  {
    "title": "M.Jones"
  },
  {
    "title": "M.Ryan"
  },
  {
    "title": "J.Kerridge"
  },
  {
    "title": "O.Daniels"
  },
  {
    "title": "I.Stanback"
  },
  {
    "title": "M.Kafka"
  },
  {
    "title": "L.Washington"
  },
  {
    "title": "B.Hartline"
  },
  {
    "title": "E.Baker"
  },
  {
    "title": "L.Ball"
  },
  {
    "title": "R.Kelly"
  },
  {
    "title": "D.Lasco"
  },
  {
    "title": "P.Richardson"
  },
  {
    "title": "D.Fales"
  },
  {
    "title": "S.Johnson"
  },
  {
    "title": "T.Boykin"
  },
  {
    "title": "D.McNabb"
  },
  {
    "title": "D.Branch"
  },
  {
    "title": "A.Sanders"
  },
  {
    "title": "T.Edwards"
  },
  {
    "title": "C.Chekwa"
  },
  {
    "title": "C.Matthews"
  },
  {
    "title": "M.Davis"
  },
  {
    "title": "L.Robinson"
  },
  {
    "title": "R.Penny"
  },
  {
    "title": "T.Watkins"
  },
  {
    "title": "K.Klug"
  },
  {
    "title": "J.Leslie"
  },
  {
    "title": "D.Dixon"
  },
  {
    "title": "J.Phillips"
  },
  {
    "title": "J.Urban"
  },
  {
    "title": "K.Burton"
  },
  {
    "title": "E.Penny"
  },
  {
    "title": "N.Sterling"
  },
  {
    "title": "L.Whitehead"
  },
  {
    "title": "Ja.Brown"
  },
  {
    "title": "A.Sendejo"
  },
  {
    "title": "M.Hollins"
  },
  {
    "title": "T.Wilson"
  },
  {
    "title": "M.Palardy"
  },
  {
    "title": "J.Ebert"
  },
  {
    "title": "J.Scott"
  },
  {
    "title": "K.Carey"
  },
  {
    "title": "M.Hardesty"
  },
  {
    "title": "M.Stafford"
  },
  {
    "title": "L.Jean"
  },
  {
    "title": "D.Inman"
  },
  {
    "title": "M.Schaub"
  },
  {
    "title": "M.Unrein"
  },
  {
    "title": "C.Boswell"
  },
  {
    "title": "D.Jackson"
  },
  {
    "title": "Mi.Williams"
  },
  {
    "title": "B.Cottam"
  },
  {
    "title": "J.Hill"
  },
  {
    "title": "Dn.Thomas"
  },
  {
    "title": "I.Trufant"
  },
  {
    "title": "G.Hoskins"
  },
  {
    "title": "P.Manning"
  },
  {
    "title": "N.Paul"
  },
  {
    "title": "J.Tucker"
  },
  {
    "title": "Q.Patton"
  },
  {
    "title": "J.Smith-Schuster"
  },
  {
    "title": "A.Stecker"
  },
  {
    "title": "D.Karim"
  },
  {
    "title": "Delanie.Walker"
  },
  {
    "title": "M.Mason"
  },
  {
    "title": "V.McDonald"
  },
  {
    "title": "G.Whimper"
  },
  {
    "title": "Jo.Brown"
  },
  {
    "title": "S.Aiken"
  },
  {
    "title": "C.Jones"
  },
  {
    "title": "T.White"
  },
  {
    "title": "D.Hopkins"
  },
  {
    "title": "C.Hogan"
  },
  {
    "title": "Jo.Freeman"
  },
  {
    "title": "J.Landry"
  },
  {
    "title": "D.Jones"
  },
  {
    "title": "G.Atkinson III"
  },
  {
    "title": "M.Wilson"
  },
  {
    "title": "K.Allen"
  },
  {
    "title": "J.Kerley"
  },
  {
    "title": "J.Goff"
  },
  {
    "title": "A.Sherman"
  },
  {
    "title": "A.Hall"
  },
  {
    "title": "E.Manuel"
  },
  {
    "title": "S.Lanning"
  },
  {
    "title": "J.McKnight"
  },
  {
    "title": "M.Lawrence"
  },
  {
    "title": "K.Johnson"
  },
  {
    "title": "G.Everett"
  },
  {
    "title": "C.Keenum"
  },
  {
    "title": "J.Clausen"
  },
  {
    "title": "G.Kittle"
  },
  {
    "title": "C.Hamilton"
  },
  {
    "title": "P.Thomas"
  },
  {
    "title": "R.Fitzpatrick"
  },
  {
    "title": "S.McGrath"
  },
  {
    "title": "N.Agholor"
  },
  {
    "title": "M.Mariani"
  },
  {
    "title": "B.St. Pierre (3rd QB)"
  },
  {
    "title": "D.Posey"
  },
  {
    "title": "R.Lewis"
  },
  {
    "title": "M.Simms"
  },
  {
    "title": "C.Mitchell"
  },
  {
    "title": "D.Jarrett"
  },
  {
    "title": "R.White"
  },
  {
    "title": "W.Welker"
  },
  {
    "title": "P.Ricard"
  },
  {
    "title": "M.Evans"
  },
  {
    "title": "T.Higbee"
  },
  {
    "title": "D.Savage"
  },
  {
    "title": "O.Howard"
  },
  {
    "title": "C.Thompson"
  },
  {
    "title": "L.Polite"
  },
  {
    "title": "C.Henry"
  },
  {
    "title": "J.Butler"
  },
  {
    "title": "P.Dorsett"
  },
  {
    "title": "G.Holmes"
  },
  {
    "title": "C.Patterson"
  },
  {
    "title": "A.McCoy"
  },
  {
    "title": "K.Moore"
  },
  {
    "title": "S.Koch"
  },
  {
    "title": "C.Core"
  },
  {
    "title": "J.Parmele"
  },
  {
    "title": "JulioJones"
  },
  {
    "title": "R.Jennings"
  },
  {
    "title": "J.Felton"
  },
  {
    "title": "B.Bell"
  },
  {
    "title": "L.Hawkins"
  },
  {
    "title": "L.Jones"
  },
  {
    "title": "M.Wheaton"
  },
  {
    "title": "J.Doctson"
  },
  {
    "title": "K.White"
  },
  {
    "title": "J.Carlson"
  },
  {
    "title": "J.Akins"
  },
  {
    "title": "K.Bell"
  },
  {
    "title": "W.Yeatman"
  },
  {
    "title": "P.DiMarco"
  },
  {
    "title": "D.Coats"
  },
  {
    "title": "B.Stokley"
  },
  {
    "title": "B.Parker"
  },
  {
    "title": "B.Addison"
  },
  {
    "title": "D.Rogers"
  },
  {
    "title": "W.Wright"
  },
  {
    "title": "K.Redfern"
  },
  {
    "title": "D.Westbrook"
  },
  {
    "title": "D.Braverman"
  },
  {
    "title": "K.Taylor"
  },
  {
    "title": "Q.Porter"
  },
  {
    "title": "T.Way"
  },
  {
    "title": "R.D'Imperio"
  },
  {
    "title": "T.Swoopes"
  },
  {
    "title": "L.Green"
  },
  {
    "title": "M.McGloin"
  },
  {
    "title": "B.Wilds"
  },
  {
    "title": "D.Dickerson"
  },
  {
    "title": "Alf.Smith"
  },
  {
    "title": "C.Coleman"
  },
  {
    "title": "S.Burton"
  },
  {
    "title": "D.Kizer"
  },
  {
    "title": "B.James"
  },
  {
    "title": "K.Boss"
  },
  {
    "title": "M.Leshoure"
  },
  {
    "title": "P.Burress"
  },
  {
    "title": "J.Simpson"
  },
  {
    "title": "H.Smith"
  },
  {
    "title": "Q.Cosby"
  },
  {
    "title": "R.Maui'a"
  },
  {
    "title": "B.Eldridge"
  },
  {
    "title": "H.Douglas"
  },
  {
    "title": "A.Derby"
  },
  {
    "title": "C.Prosise"
  },
  {
    "title": "R.Nassib"
  },
  {
    "title": "C.Prosinski"
  },
  {
    "title": "B.Raji"
  },
  {
    "title": "R.Hughes"
  },
  {
    "title": "J.Krause"
  },
  {
    "title": "D.Wylie"
  },
  {
    "title": "R.Hodges"
  },
  {
    "title": "W.Gallman"
  },
  {
    "title": "C.Rainey"
  },
  {
    "title": "G.Salas"
  },
  {
    "title": "J.Rosen"
  },
  {
    "title": "J.Arenas"
  },
  {
    "title": "Wi.Johnson"
  },
  {
    "title": "C.Stevens"
  },
  {
    "title": "D.Poe"
  },
  {
    "title": "M.Norris"
  },
  {
    "title": "Al.Robinson"
  },
  {
    "title": "L.Wester"
  },
  {
    "title": "L.Johnson"
  },
  {
    "title": "J.Allen"
  },
  {
    "title": "V.Bolden"
  },
  {
    "title": "M.Tolbert"
  },
  {
    "title": "D.Noble"
  },
  {
    "title": "N.Mullens"
  },
  {
    "title": "I.Pead"
  },
  {
    "title": "C.Batch"
  },
  {
    "title": "C.Harkey"
  },
  {
    "title": "R.Jones"
  },
  {
    "title": "M.Goodson"
  },
  {
    "title": "N.Berhe"
  },
  {
    "title": "C.Ponder"
  },
  {
    "title": "J.Marshall"
  },
  {
    "title": "R.Thomas"
  },
  {
    "title": "B.Batch"
  },
  {
    "title": "O.Marecic"
  },
  {
    "title": "D.Cook"
  },
  {
    "title": "J.Grimes"
  },
  {
    "title": "S.Breaston"
  },
  {
    "title": "S.Slaton"
  },
  {
    "title": "Z.Ertz"
  },
  {
    "title": "A.Whitworth"
  },
  {
    "title": "M.Owens"
  },
  {
    "title": "J.Edelman"
  },
  {
    "title": "D.Stallworth"
  },
  {
    "title": "M.Bennett"
  },
  {
    "title": "J.Reitz"
  },
  {
    "title": "B.Obomanu"
  },
  {
    "title": "A.Jackson"
  },
  {
    "title": "Mar.Moore"
  },
  {
    "title": "R.Wallace"
  },
  {
    "title": "M.Brown"
  },
  {
    "title": "B.Bolen"
  },
  {
    "title": "J.O'Connell"
  },
  {
    "title": "V.Leach"
  },
  {
    "title": "D.Hagan"
  },
  {
    "title": "A.Hernandez"
  },
  {
    "title": "M.Hall"
  },
  {
    "title": "T.Thompson"
  },
  {
    "title": "F.Davis"
  },
  {
    "title": "B.Berrian"
  },
  {
    "title": "B.Favre"
  },
  {
    "title": "R.Meachem"
  },
  {
    "title": "V.Smith"
  },
  {
    "title": "B.LaFell"
  },
  {
    "title": "J.Leggett"
  },
  {
    "title": "K.Coutee"
  },
  {
    "title": "G.Wolfe"
  },
  {
    "title": "E.Manning"
  },
  {
    "title": "T.McBride"
  },
  {
    "title": "P.Rivers"
  },
  {
    "title": "R.Smith"
  },
  {
    "title": "N.Kasa"
  },
  {
    "title": "I.Ford"
  },
  {
    "title": "K.Moreno"
  },
  {
    "title": "C.Whitehurst"
  },
  {
    "title": "D.Waller"
  },
  {
    "title": "M.Jennings"
  },
  {
    "title": "L.Long"
  },
  {
    "title": "J.Boyce"
  },
  {
    "title": "M.Murphy"
  },
  {
    "title": "R.Hillman"
  },
  {
    "title": "C.Sims"
  },
  {
    "title": "O.O'Neal"
  },
  {
    "title": "J.Nordin"
  },
  {
    "title": "Ch.Johnson"
  },
  {
    "title": "B.Manumaleuna"
  },
  {
    "title": "D.McDonald"
  },
  {
    "title": "R.Moats"
  },
  {
    "title": "R.Brown"
  },
  {
    "title": "G.Dieter"
  },
  {
    "title": "K.Toston"
  },
  {
    "title": "T.Magee"
  },
  {
    "title": "A.Hawkins"
  },
  {
    "title": "D.Rosario"
  },
  {
    "title": "H.Evans"
  },
  {
    "title": "M.Lee"
  },
  {
    "title": "M.Giordano"
  },
  {
    "title": "A.Kamara"
  },
  {
    "title": "C.Worthy"
  },
  {
    "title": "K.Colbert"
  },
  {
    "title": "R.Wingo"
  },
  {
    "title": "M.Tonga"
  },
  {
    "title": "A.Ellington"
  },
  {
    "title": "K.Winslow"
  },
  {
    "title": "E.Saubert"
  },
  {
    "title": "T.Madden"
  },
  {
    "title": "T.Alualu"
  },
  {
    "title": "J.Matthews"
  },
  {
    "title": "J.Howard"
  },
  {
    "title": "L.Sweed"
  },
  {
    "title": "K.Huggins"
  },
  {
    "title": "J.Franklin"
  },
  {
    "title": "J.Haynos"
  },
  {
    "title": "D.Mason"
  },
  {
    "title": "J.Griffith"
  },
  {
    "title": "C.Schilens"
  },
  {
    "title": "R.Royal"
  },
  {
    "title": "C.Frye"
  },
  {
    "title": "K.Stills"
  },
  {
    "title": "J.Rudock"
  },
  {
    "title": "C.Hansen"
  },
  {
    "title": "D.Funchess"
  },
  {
    "title": "T.Clutts"
  },
  {
    "title": "A.Crumpler"
  },
  {
    "title": "C.McCaffrey"
  },
  {
    "title": "G.Olsen"
  },
  {
    "title": "B.Gibson"
  },
  {
    "title": "C.Franklin"
  },
  {
    "title": "T.Heap"
  },
  {
    "title": "W.Hunter"
  },
  {
    "title": "G.Jenkins"
  },
  {
    "title": "D.Carr"
  },
  {
    "title": "T.Rawls"
  },
  {
    "title": "M.Tennant"
  },
  {
    "title": "C.Santos"
  },
  {
    "title": "T.Bridgewater"
  },
  {
    "title": "S.Mannion"
  },
  {
    "title": "C.Taylor"
  },
  {
    "title": "C.Clement"
  },
  {
    "title": "C.Ridley"
  },
  {
    "title": "Z.Pascal"
  },
  {
    "title": "N.Boyle"
  },
  {
    "title": "D.McFadden"
  },
  {
    "title": "D.Archer"
  },
  {
    "title": "B.Rainey"
  },
  {
    "title": "K.Britt"
  },
  {
    "title": "I.Bruce"
  },
  {
    "title": "C.Roby"
  },
  {
    "title": "M.Sanchez"
  },
  {
    "title": "T.Holliday"
  },
  {
    "title": "A.Dalton"
  },
  {
    "title": "C.Chambers"
  },
  {
    "title": "T.Cannon"
  },
  {
    "title": "A.Hooper"
  },
  {
    "title": "M.Stafford (3rd QB)"
  },
  {
    "title": "D.Penn"
  },
  {
    "title": "K.Sheets"
  },
  {
    "title": "S.Lechler"
  },
  {
    "title": "B.Colquitt"
  },
  {
    "title": "S.Gado"
  },
  {
    "title": "C.Bojorquez"
  },
  {
    "title": "T.Kelce"
  },
  {
    "title": "F.Summers"
  },
  {
    "title": "D.Baldwin"
  },
  {
    "title": "S.Keo"
  },
  {
    "title": "J.Driskel"
  },
  {
    "title": "B.Brown"
  },
  {
    "title": "J.Holley"
  },
  {
    "title": "D.Epps"
  },
  {
    "title": "G.Tate"
  },
  {
    "title": "J.Ajayi"
  },
  {
    "title": "B.Tate"
  },
  {
    "title": "K.Juszczyk"
  },
  {
    "title": "D.McCluster"
  },
  {
    "title": "M.Breida"
  },
  {
    "title": "D.Brown"
  },
  {
    "title": "D.Colquitt"
  },
  {
    "title": "T.Taylor"
  },
  {
    "title": "J.Harper"
  },
  {
    "title": "Q.Ganther"
  },
  {
    "title": "A.Miller"
  },
  {
    "title": "K.Raymond"
  },
  {
    "title": "T.Thigpen"
  },
  {
    "title": "T.Jackson"
  },
  {
    "title": "D.Newsome"
  },
  {
    "title": "S.Martin"
  },
  {
    "title": "D.Thompson"
  },
  {
    "title": "M.Dayes"
  },
  {
    "title": "K.Byard"
  },
  {
    "title": "C.Buckhalter"
  },
  {
    "title": "D.Presley"
  },
  {
    "title": "B.Quinn"
  },
  {
    "title": "A.Villanueva"
  },
  {
    "title": "A.Blake"
  },
  {
    "title": "R.Quigley"
  },
  {
    "title": "J.Aubrey"
  },
  {
    "title": "B.Treggs"
  },
  {
    "title": "Da.Williams"
  },
  {
    "title": "D.Butler"
  },
  {
    "title": "D.Lee"
  },
  {
    "title": "N.Jacobs"
  },
  {
    "title": "J.Dobbs"
  },
  {
    "title": "B.Jacobs"
  },
  {
    "title": "J.Knox"
  },
  {
    "title": "J.Thomas"
  },
  {
    "title": "C.Helfet"
  },
  {
    "title": "V.Jackson"
  },
  {
    "title": "Ma.Moore"
  },
  {
    "title": "A.Boldin"
  },
  {
    "title": "M.Bosher"
  },
  {
    "title": "S.Diggs"
  },
  {
    "title": "M.Goodwin"
  },
  {
    "title": "E.Arceneaux"
  },
  {
    "title": "R.Graham"
  },
  {
    "title": "J.Collins"
  },
  {
    "title": "E.Page"
  },
  {
    "title": "B.Scott"
  },
  {
    "title": "T.Varga"
  },
  {
    "title": "B.Hoyer"
  },
  {
    "title": "J.McGraw"
  },
  {
    "title": "F.Gore"
  },
  {
    "title": "John.Brown"
  },
  {
    "title": "T.Burton"
  },
  {
    "title": "A.Jones"
  },
  {
    "title": "J.Bidwell"
  },
  {
    "title": "B.Patrick"
  },
  {
    "title": "O.Mughelli"
  },
  {
    "title": "Josh.Brown"
  },
  {
    "title": "R.Mostert"
  },
  {
    "title": "I.Fruechte"
  },
  {
    "title": "L.Taliaferro"
  },
  {
    "title": "A.Armstrong"
  },
  {
    "title": "D.Keller"
  },
  {
    "title": "J.Kuhn"
  },
  {
    "title": "E.Ebron"
  },
  {
    "title": "M.Palmer"
  },
  {
    "title": "J.Thompson"
  },
  {
    "title": "Mat.Moore"
  },
  {
    "title": "K.Ford"
  },
  {
    "title": "M.Walton"
  },
  {
    "title": "M.Furrey"
  },
  {
    "title": "J.Jenkins"
  },
  {
    "title": "N.Byham"
  },
  {
    "title": "P.Cooper"
  },
  {
    "title": "S.Maneri"
  },
  {
    "title": "C.Morrah"
  },
  {
    "title": "J.Webb"
  },
  {
    "title": "D.Burnett"
  },
  {
    "title": "G.Whalen"
  },
  {
    "title": "T.Humphrey"
  },
  {
    "title": "B.Sowell"
  },
  {
    "title": "L.Maroney"
  },
  {
    "title": "B.Ellington"
  },
  {
    "title": "T.Beckum"
  },
  {
    "title": "D.Street"
  },
  {
    "title": "D.Graham"
  },
  {
    "title": "A.Reisner"
  },
  {
    "title": "A.Rolle"
  },
  {
    "title": "D.Smelter"
  },
  {
    "title": "F.Jackson"
  },
  {
    "title": "K.Hall"
  },
  {
    "title": "S.Morris"
  },
  {
    "title": "B.Perriman"
  },
  {
    "title": "D.Avery"
  },
  {
    "title": "C.Henne"
  },
  {
    "title": "R.Golden"
  },
  {
    "title": "T.Houshmandzadeh"
  },
  {
    "title": "T.Bohanon"
  },
  {
    "title": "R.Kelley"
  },
  {
    "title": "C.Gronkowski"
  },
  {
    "title": "D.Pitta"
  },
  {
    "title": "D.Sampson"
  },
  {
    "title": "D.Adams"
  },
  {
    "title": "H.Ward"
  },
  {
    "title": "Z.Line"
  },
  {
    "title": "J.Cribbs"
  },
  {
    "title": "S.Chapas"
  },
  {
    "title": "C.Beasley"
  },
  {
    "title": "R.Matthews"
  },
  {
    "title": "M.Turner"
  },
  {
    "title": "M.Clayton"
  },
  {
    "title": "R.Succop"
  },
  {
    "title": "V.Haynes"
  },
  {
    "title": "E.Swoope"
  },
  {
    "title": "M.White"
  },
  {
    "title": "C.Michael"
  },
  {
    "title": "G.Coffee"
  },
  {
    "title": "B.Weeden"
  },
  {
    "title": "Ale.Smith"
  },
  {
    "title": "O.Schmitt"
  },
  {
    "title": "J.Skelton"
  },
  {
    "title": "P.Garcon"
  },
  {
    "title": "D.Nance"
  },
  {
    "title": "C.Ogbonnaya"
  },
  {
    "title": "J.Harrison"
  },
  {
    "title": "J.Hardy"
  },
  {
    "title": "T.Price"
  },
  {
    "title": "St.Johnson"
  },
  {
    "title": "R.McCloud"
  },
  {
    "title": "B.Johnson"
  },
  {
    "title": "S.Wynn"
  },
  {
    "title": "D.Paulson"
  },
  {
    "title": "Ka.Williams"
  },
  {
    "title": "K.Norwood"
  },
  {
    "title": "M.Vick"
  },
  {
    "title": "A.Quarless"
  },
  {
    "title": "O.Beckham Jr."
  },
  {
    "title": "D.Calhoun"
  },
  {
    "title": "J.Morgan"
  },
  {
    "title": "S.Considine"
  },
  {
    "title": "C.Herndon"
  },
  {
    "title": "L.Evans"
  },
  {
    "title": "R.Moss"
  },
  {
    "title": "J.Hamm"
  },
  {
    "title": "C.Cook"
  },
  {
    "title": "R.Foster"
  },
  {
    "title": "R.Ross"
  },
  {
    "title": "J.Cameron"
  },
  {
    "title": "C.Painter"
  },
  {
    "title": "T.Watson"
  },
  {
    "title": "T.Hightower"
  },
  {
    "title": "G.Smith"
  },
  {
    "title": "E.Sanders"
  },
  {
    "title": "B.Mayfield"
  },
  {
    "title": "D.Hilliard"
  },
  {
    "title": "J.Kent"
  },
  {
    "title": "M.Hedgecock"
  },
  {
    "title": "S.Spach"
  },
  {
    "title": "T.Sharpe"
  },
  {
    "title": "B.Powell"
  },
  {
    "title": "D.Nelson"
  },
  {
    "title": "A.Edwards"
  },
  {
    "title": "I.Abdul-Quddus"
  },
  {
    "title": "E.Eagan"
  },
  {
    "title": "J.Watt"
  },
  {
    "title": "B.Smith"
  },
  {
    "title": "P.Crayton"
  },
  {
    "title": "R.Lockette"
  },
  {
    "title": "D.Hixon"
  },
  {
    "title": "M.Cassel"
  },
  {
    "title": "R.Randle"
  },
  {
    "title": "Da.Johnson"
  },
  {
    "title": "D.Bowe"
  },
  {
    "title": "C.Shaw"
  },
  {
    "title": "S.Patton"
  },
  {
    "title": "C.Spiller"
  },
  {
    "title": "R.Woods"
  },
  {
    "title": "A.Randle El"
  },
  {
    "title": "B.Maynard"
  },
  {
    "title": "J.Townsend"
  },
  {
    "title": "Ja. Brown"
  },
  {
    "title": "R.James"
  },
  {
    "title": "L.Vickers"
  },
  {
    "title": "T.Yates"
  },
  {
    "title": "R.Anderson"
  },
  {
    "title": "T.Young"
  },
  {
    "title": "J.Kitna"
  },
  {
    "title": "D.Johnson"
  },
  {
    "title": "C.Palmer"
  },
  {
    "title": "J.Rodgers"
  },
  {
    "title": "J.Gordon"
  },
  {
    "title": "W.Beatty"
  },
  {
    "title": "O.Beckham"
  },
  {
    "title": "L.Daniels"
  },
  {
    "title": "G.Celek"
  },
  {
    "title": "L.McCown"
  },
  {
    "title": "M.Darr"
  },
  {
    "title": "J.Campbell"
  },
  {
    "title": "D.Foreman"
  },
  {
    "title": "K.Brock"
  },
  {
    "title": "J.Mickens"
  },
  {
    "title": "K.Benjamin"
  },
  {
    "title": "J.Williams"
  },
  {
    "title": "R.Lindley"
  },
  {
    "title": "Dar.Williams"
  },
  {
    "title": "R.Denney"
  },
  {
    "title": "T.McEvoy"
  },
  {
    "title": "T.Lewis"
  },
  {
    "title": "B.Fowler"
  },
  {
    "title": "D.Alexander"
  },
  {
    "title": "K.Cone"
  },
  {
    "title": "J.Todman"
  },
  {
    "title": "D.Watson"
  },
  {
    "title": "V.Mayle"
  },
  {
    "title": "M.Mack"
  },
  {
    "title": "D.Bruton"
  },
  {
    "title": "R.Hewitt"
  },
  {
    "title": "Sh.Hill"
  },
  {
    "title": "B.Pierce"
  },
  {
    "title": "K.Boothe"
  },
  {
    "title": "J.Johnson"
  },
  {
    "title": "L.Brown"
  },
  {
    "title": "J.Horne"
  },
  {
    "title": "J.Chesson"
  },
  {
    "title": "C.Hamlett"
  },
  {
    "title": "C.Fejedelem"
  },
  {
    "title": "M.Higgins"
  },
  {
    "title": "G.Harrell"
  },
  {
    "title": "R.Murphy"
  },
  {
    "title": "D.Clowney"
  },
  {
    "title": "D.Foster"
  },
  {
    "title": "A.Luck"
  },
  {
    "title": "S.Rice"
  },
  {
    "title": "J.Cook"
  },
  {
    "title": "T.Eifert"
  },
  {
    "title": "C.Coffman"
  },
  {
    "title": "P.Perkins"
  },
  {
    "title": "J.Charles"
  },
  {
    "title": "N.Peterman"
  },
  {
    "title": "J.Cutler"
  },
  {
    "title": "D.Brees"
  },
  {
    "title": "W.Parker"
  },
  {
    "title": "N.Ebner"
  },
  {
    "title": "D.Cruikshank"
  },
  {
    "title": "C.Cooley"
  },
  {
    "title": "T.Heinicke"
  },
  {
    "title": "JO.Brown"
  },
  {
    "title": "D.Carrier"
  },
  {
    "title": "S.Stroughter"
  },
  {
    "title": "J.Dray"
  },
  {
    "title": "K.Lauletta"
  },
  {
    "title": "D.Smith"
  },
  {
    "title": "T.Doss"
  },
  {
    "title": "B.Myers"
  },
  {
    "title": "S.DeValve"
  },
  {
    "title": "G.Fant"
  },
  {
    "title": "G.Swaim"
  },
  {
    "title": "K.Sperry"
  },
  {
    "title": "K.Aiken"
  },
  {
    "title": "J.Talley"
  },
  {
    "title": "M.Alie-Cox"
  },
  {
    "title": "J.Perkins"
  },
  {
    "title": "A.Morris"
  },
  {
    "title": "S.Nelson"
  },
  {
    "title": "J.Cotchery"
  },
  {
    "title": "C.Peake"
  },
  {
    "title": "A.Armah"
  },
  {
    "title": "B.Pinion"
  },
  {
    "title": "R.Higgins"
  },
  {
    "title": "B.Oliver"
  },
  {
    "title": "K.Osgood"
  },
  {
    "title": "B.Banks"
  },
  {
    "title": "C.Manhertz"
  },
  {
    "title": "A.Gardner"
  },
  {
    "title": "R.Bartel"
  },
  {
    "title": "D.Johnson Jr"
  },
  {
    "title": "D.Watt"
  },
  {
    "title": "M.Dickson"
  },
  {
    "title": "I.Burse"
  },
  {
    "title": "D.Ausberry"
  },
  {
    "title": "Q.Lawrence"
  },
  {
    "title": "C.Benson"
  },
  {
    "title": "K.Long"
  },
  {
    "title": "T.Jones"
  },
  {
    "title": "V.Cruz"
  },
  {
    "title": "I.Momah"
  },
  {
    "title": "A.Benn"
  },
  {
    "title": "T.Mizzell"
  },
  {
    "title": "R.Telfer"
  },
  {
    "title": "P.Lindsay"
  },
  {
    "title": "D.Ward"
  },
  {
    "title": "A.Peterson"
  },
  {
    "title": "K.Ogletree"
  },
  {
    "title": "K.Zinger"
  },
  {
    "title": "C.Godwin"
  },
  {
    "title": "J.Robinson"
  },
  {
    "title": "J.Jones"
  },
  {
    "title": "G.Christian"
  },
  {
    "title": "K.Dixon"
  },
  {
    "title": "K.Hatcher"
  },
  {
    "title": "E.Gates"
  },
  {
    "title": "E.Williams"
  },
  {
    "title": "T.Bray"
  },
  {
    "title": "T.Scheffler"
  },
  {
    "title": "J.King"
  },
  {
    "title": "T.Watts"
  },
  {
    "title": "D. Thomas"
  },
  {
    "title": "K.Thompkins"
  },
  {
    "title": "K.Kolb"
  },
  {
    "title": "Matt.Moore"
  },
  {
    "title": "J.Maehl"
  },
  {
    "title": "R.Wayne"
  },
  {
    "title": "M.Slater"
  },
  {
    "title": "Jo.Webb"
  },
  {
    "title": "M.Floyd"
  },
  {
    "title": "M.Booker"
  },
  {
    "title": "M.Hill"
  },
  {
    "title": "K.Zeitler"
  },
  {
    "title": "N.Chubb"
  },
  {
    "title": "S.Holmes"
  },
  {
    "title": "D.Heyward-Bey"
  },
  {
    "title": "C.Batson"
  },
  {
    "title": "J.Ferguson"
  },
  {
    "title": "J.McNichols"
  },
  {
    "title": "L.James"
  },
  {
    "title": "J.Criner"
  },
  {
    "title": "K.Bibbs"
  },
  {
    "title": "J.Wilson"
  },
  {
    "title": "T.Collins"
  },
  {
    "title": "K.Ballage"
  },
  {
    "title": "B.Butler"
  },
  {
    "title": "H.Baskett"
  },
  {
    "title": "J.Shockey"
  },
  {
    "title": "M.Muhammad"
  },
  {
    "title": "J.Hayne"
  },
  {
    "title": "C.Harper"
  },
  {
    "title": "E.Byrd"
  },
  {
    "title": "F.Onobun"
  },
  {
    "title": "T.Wright"
  },
  {
    "title": "C.Wick"
  },
  {
    "title": "E.Lacy"
  },
  {
    "title": "E.Rodriguez"
  },
  {
    "title": "A.Pettis"
  },
  {
    "title": "T.Fiammetta"
  },
  {
    "title": "B.Hartsock"
  },
  {
    "title": "K.Cousins"
  },
  {
    "title": "C.Ivory"
  },
  {
    "title": "C.Gillmore"
  },
  {
    "title": "R.Johnson"
  },
  {
    "title": "S.Wilson"
  },
  {
    "title": "D.Reed"
  },
  {
    "title": "G.Lewis"
  },
  {
    "title": "C.Wadman"
  },
  {
    "title": "B.Moorman"
  },
  {
    "title": "S.Weatherford"
  },
  {
    "title": "S.Pulley"
  },
  {
    "title": "P.McRoberts"
  },
  {
    "title": "B.Bowman"
  },
  {
    "title": "C.Schmidt"
  },
  {
    "title": "A.Burbridge"
  },
  {
    "title": "S.Taylor"
  },
  {
    "title": "D.Washington"
  },
  {
    "title": "J.Banyard"
  },
  {
    "title": "R.Mendenhall"
  },
  {
    "title": "K.Huber"
  },
  {
    "title": "S.Thompson"
  },
  {
    "title": "E.Decker"
  },
  {
    "title": "M.Komar"
  },
  {
    "title": "Je.Johnson"
  },
  {
    "title": "A.Callaway"
  },
  {
    "title": "M.Austin"
  },
  {
    "title": "H.Miller"
  },
  {
    "title": "D.Moncrief"
  },
  {
    "title": "C.Lynch"
  },
  {
    "title": "M.James"
  },
  {
    "title": "K.Clemens"
  },
  {
    "title": "A.Dixon"
  },
  {
    "title": "A.Allen"
  },
  {
    "title": "J.Clary"
  },
  {
    "title": "J.Battle"
  },
  {
    "title": "W.Svitek"
  },
  {
    "title": "C.Fleener"
  },
  {
    "title": "A.Cromartie"
  },
  {
    "title": "A.Jeffery"
  },
  {
    "title": "M.Pruitt"
  },
  {
    "title": "I.Thomas"
  },
  {
    "title": "J.Payton"
  },
  {
    "title": "J.Ross"
  },
  {
    "title": "M.Moore"
  },
  {
    "title": "D.Murray"
  },
  {
    "title": "D.Coleman"
  },
  {
    "title": "F.Martino"
  },
  {
    "title": "S.Bailey"
  },
  {
    "title": "D.Culpepper"
  },
  {
    "title": "T.Smith"
  },
  {
    "title": "C.Gray"
  },
  {
    "title": "J.Baldwin"
  },
  {
    "title": "J.Flacco"
  },
  {
    "title": "C.Samuel"
  },
  {
    "title": "S.Ridley"
  },
  {
    "title": "R.Louis"
  },
  {
    "title": "E.Royster"
  },
  {
    "title": "D.Kreider"
  },
  {
    "title": "A.Darboh"
  },
  {
    "title": "J.Bellamy"
  },
  {
    "title": "M.Thigpen"
  },
  {
    "title": "B.Jarwin"
  },
  {
    "title": "C.Conley"
  },
  {
    "title": "J.Maclin"
  },
  {
    "title": "C.Anderson"
  },
  {
    "title": "J.Nesbit"
  },
  {
    "title": "P.O'Donnell"
  },
  {
    "title": "J.Newsome"
  },
  {
    "title": "M.Prater"
  },
  {
    "title": "T.Poole"
  },
  {
    "title": "C.Polk"
  },
  {
    "title": "D.Northcutt"
  },
  {
    "title": "L.Hamilton"
  },
  {
    "title": "B.Kern"
  },
  {
    "title": "J.Hawley"
  },
  {
    "title": "C.Newton"
  },
  {
    "title": "D.McCray"
  },
  {
    "title": "J.McKie"
  },
  {
    "title": "S.Vereen"
  },
  {
    "title": "C.Phillips"
  },
  {
    "title": "J.Bell"
  },
  {
    "title": "S.Smith Sr."
  },
  {
    "title": "T.Ervin"
  },
  {
    "title": "M.Bush"
  },
  {
    "title": "E.Elliott"
  },
  {
    "title": "T.Pike (3rd QB)"
  },
  {
    "title": "A.Jenkins"
  },
  {
    "title": "T.Yoder"
  },
  {
    "title": "J.Stupar"
  },
  {
    "title": "B.Croyle"
  },
  {
    "title": "J.Hanna"
  },
  {
    "title": "J.McKissic"
  },
  {
    "title": "K.Warner"
  },
  {
    "title": "D.Pettis"
  },
  {
    "title": "B.Coleman"
  },
  {
    "title": "B.Quick"
  },
  {
    "title": "R.Purvis"
  },
  {
    "title": "B.Daniels"
  },
  {
    "title": "A.Traylor"
  },
  {
    "title": "W.Saunders"
  },
  {
    "title": "C.Fitzsimmons"
  },
  {
    "title": "R.Mahaffey"
  },
  {
    "title": "D.Moore"
  },
  {
    "title": "M.Sellers"
  },
  {
    "title": "E.St. Brown"
  },
  {
    "title": "S.Hubbard"
  },
  {
    "title": "C.Rogers"
  },
  {
    "title": "T.Coleman"
  },
  {
    "title": "S.Shields"
  },
  {
    "title": "L.Carroo"
  },
  {
    "title": "P.Turner"
  },
  {
    "title": "K.Davis"
  },
  {
    "title": "B.Marshall"
  },
  {
    "title": "D.Byrd"
  },
  {
    "title": "C.Wells"
  },
  {
    "title": "G.Griffin"
  },
  {
    "title": "G.Estandia"
  },
  {
    "title": "L.Williams"
  },
  {
    "title": "E.Smith"
  },
  {
    "title": "M.Wallace"
  },
  {
    "title": "R.Griffin III"
  },
  {
    "title": "J.Russell"
  },
  {
    "title": "C.Hanie (3rd QB)"
  },
  {
    "title": "J.Janis"
  },
  {
    "title": "P.Tanner"
  },
  {
    "title": "B.Pascoe"
  },
  {
    "title": "S.Ryan"
  },
  {
    "title": "R.McCarron"
  },
  {
    "title": "J.Fauria"
  },
  {
    "title": "A.Arrington"
  },
  {
    "title": "D.Ware"
  },
  {
    "title": "E.McGuire"
  },
  {
    "title": "B.Leonhardt"
  },
  {
    "title": "J.Davis"
  },
  {
    "title": "M.Lewis"
  },
  {
    "title": "S.Hill"
  },
  {
    "title": "D.Goedert"
  },
  {
    "title": "T.Kroft"
  },
  {
    "title": "A.Hunt"
  },
  {
    "title": "K.Dorsey"
  },
  {
    "title": "M.Iupati"
  },
  {
    "title": "J.Garoppolo"
  },
  {
    "title": "J.Casey"
  },
  {
    "title": "Alex Smith"
  },
  {
    "title": "R.Gordon"
  },
  {
    "title": "D.Carter"
  },
  {
    "title": "C.Sutton"
  },
  {
    "title": "W.Tukuafu"
  },
  {
    "title": "T.Pryor Sr."
  },
  {
    "title": "R.Dixon"
  },
  {
    "title": "S.Suisham"
  },
  {
    "title": "D.Schultz"
  },
  {
    "title": "D.Fine"
  },
  {
    "title": "J.Ford"
  },
  {
    "title": "E.Flowers"
  },
  {
    "title": "G.Russell"
  },
  {
    "title": "M.Sanu"
  },
  {
    "title": "C.Washington"
  },
  {
    "title": "C.Fuller"
  },
  {
    "title": "L.Hankerson"
  },
  {
    "title": "M.LaCosse"
  },
  {
    "title": "J.McCown"
  },
  {
    "title": "N.Foles"
  },
  {
    "title": "M.Hart"
  },
  {
    "title": "D.Freeman"
  },
  {
    "title": "A.Turzilli"
  },
  {
    "title": "M.Harris"
  },
  {
    "title": "L.McClain"
  },
  {
    "title": "J.Babineaux"
  },
  {
    "title": "J.Harris"
  },
  {
    "title": "T.Johnson"
  },
  {
    "title": "G.Winn"
  },
  {
    "title": "K.Bourne"
  },
  {
    "title": "De.Williams"
  },
  {
    "title": "E.Jones"
  },
  {
    "title": "D.Prescott"
  },
  {
    "title": "J.Grant"
  },
  {
    "title": "T.Sutton"
  },
  {
    "title": "Q.Bray"
  },
  {
    "title": "B.Hill"
  },
  {
    "title": "K.Golladay"
  },
  {
    "title": "M.Matthews"
  },
  {
    "title": "A.Ripkowski"
  },
  {
    "title": "T.Gafford"
  },
  {
    "title": "C.Crocker"
  },
  {
    "title": "C.Martin"
  },
  {
    "title": "J.Higgins"
  },
  {
    "title": "E.Weddle"
  },
  {
    "title": "T.Yeldon"
  },
  {
    "title": "J.Dwyer"
  },
  {
    "title": "K.Tandy"
  },
  {
    "title": "Ryan"
  },
  {
    "title": "J.Senn"
  },
  {
    "title": "M.Robinson"
  },
  {
    "title": "K.Faulk"
  },
  {
    "title": "T.Pope"
  },
  {
    "title": "A.Thielen"
  },
  {
    "title": "R.Ventrone"
  },
  {
    "title": "C.Wood"
  },
  {
    "title": "T.Gonzalez"
  },
  {
    "title": "D.Lewis"
  },
  {
    "title": "S.McGee"
  },
  {
    "title": "T.Gallarda"
  },
  {
    "title": "S.Simonson"
  },
  {
    "title": "C.Brinkley"
  },
  {
    "title": "J.Fisher"
  },
  {
    "title": "M.Slauson"
  },
  {
    "title": "D.Richardson"
  },
  {
    "title": "A.Lewis"
  },
  {
    "title": "G.Banks"
  },
  {
    "title": "R.Housler"
  },
  {
    "title": "M.Lynch"
  },
  {
    "title": "T.Lewan"
  },
  {
    "title": "C.Rush"
  },
  {
    "title": "A.Snyder"
  },
  {
    "title": "S.Hakim"
  },
  {
    "title": "B.Bajema"
  },
  {
    "title": "S.Gibson"
  },
  {
    "title": "J.Develin"
  },
  {
    "title": "J.Hekker"
  },
  {
    "title": "B.Walters"
  },
  {
    "title": "M.McCaffrey"
  },
  {
    "title": "L.Smith"
  },
  {
    "title": "D.Akers"
  },
  {
    "title": "D.Arnold"
  },
  {
    "title": "S.Coates"
  },
  {
    "title": "T.Niklas"
  },
  {
    "title": "D.Reynaud"
  },
  {
    "title": "B.Koyack"
  },
  {
    "title": "L.Miller"
  },
  {
    "title": "M.Willis"
  },
  {
    "title": "N.Bellore"
  },
  {
    "title": "J.Wims"
  },
  {
    "title": "B.Lloyd"
  },
  {
    "title": "R.Martin"
  },
  {
    "title": "M.Lengel"
  },
  {
    "title": "K.Hunt"
  },
  {
    "title": "T.Underwood"
  },
  {
    "title": "T.Gentry"
  },
  {
    "title": "Z.Zenner"
  },
  {
    "title": "L.Weaver"
  },
  {
    "title": "C.Cloherty"
  },
  {
    "title": "C.Kluwe"
  },
  {
    "title": "A.Johnson"
  },
  {
    "title": "Charles.Johnson"
  },
  {
    "title": "L.Murphy"
  },
  {
    "title": "R.Rodgers"
  },
  {
    "title": "K.Mumphery"
  },
  {
    "title": "J.Randle"
  },
  {
    "title": "L.Toilolo"
  },
  {
    "title": "St. Johnson"
  },
  {
    "title": "N.Brown"
  },
  {
    "title": "J.Smith"
  },
  {
    "title": "J.Finley"
  },
  {
    "title": "T.Austin"
  },
  {
    "title": "W.Smallwood"
  },
  {
    "title": "C.Grant"
  },
  {
    "title": "J.Iosefa"
  },
  {
    "title": "K.Drake"
  },
  {
    "title": "Ko.Smith"
  },
  {
    "title": "S.Greene"
  },
  {
    "title": "T.Siemian"
  },
  {
    "title": "G.Edwards"
  },
  {
    "title": "J.Agnew"
  },
  {
    "title": "M.Purify"
  },
  {
    "title": "R.Taylor"
  },
  {
    "title": "K.Smith"
  },
  {
    "title": "X.Grimble"
  },
  {
    "title": "T.King"
  },
  {
    "title": "L.Hilliard"
  },
  {
    "title": "Kv.Smith"
  },
  {
    "title": "S.Giguere"
  },
  {
    "title": "D.Martin"
  },
  {
    "title": "Q.Enunwa"
  },
  {
    "title": "T.West"
  },
  {
    "title": "J.Peppers"
  },
  {
    "title": "J.Taylor"
  },
  {
    "title": "A.Gates"
  },
  {
    "title": "M.Madu"
  },
  {
    "title": "V.Tucker"
  },
  {
    "title": "M.Johnson"
  },
  {
    "title": "R.Whalen"
  },
  {
    "title": "B.Wing"
  },
  {
    "title": "L.McCoy"
  },
  {
    "title": "J.Fargas"
  },
  {
    "title": "B.Bersin"
  },
  {
    "title": "P.Edwards"
  },
  {
    "title": "R.Broyles"
  },
  {
    "title": "C.West"
  },
  {
    "title": "J.Prosch"
  },
  {
    "title": "L.Blount"
  },
  {
    "title": "E.Buckley"
  },
  {
    "title": "K.Collins"
  },
  {
    "title": "M.Oher"
  },
  {
    "title": "J.Winston"
  },
  {
    "title": "T.Santi"
  },
  {
    "title": "S.Havili"
  },
  {
    "title": "X.Omon"
  },
  {
    "title": "C.Sims III"
  },
  {
    "title": "J.Kumerow"
  },
  {
    "title": "C.Smith"
  },
  {
    "title": "B.Jackson"
  },
  {
    "title": "A.Bradford"
  },
  {
    "title": "A.Collins"
  },
  {
    "title": "L.Jordan"
  },
  {
    "title": "C.Hanie"
  },
  {
    "title": "Z.Tipton"
  },
  {
    "title": "A.Tate"
  },
  {
    "title": "R.Ellison"
  },
  {
    "title": "A.Andrews"
  },
  {
    "title": "D.Williams"
  },
  {
    "title": "T.Boyd"
  },
  {
    "title": "L.Rankin"
  },
  {
    "title": "M.Grice"
  },
  {
    "title": "D.Moye"
  },
  {
    "title": "B.Scaife"
  },
  {
    "title": "J.Gaffney"
  },
  {
    "title": "R.Shepard"
  },
  {
    "title": "P.Cobbs"
  },
  {
    "title": "D.Clark"
  },
  {
    "title": "Dom.Davis"
  },
  {
    "title": "M.Vrabel"
  },
  {
    "title": "M.Thomas"
  },
  {
    "title": "J.Ryan"
  },
  {
    "title": "M.Mitchell"
  },
  {
    "title": "N.Tahi"
  },
  {
    "title": "C.Kirk"
  },
  {
    "title": "D.Thomas"
  },
  {
    "title": "W.Fuller"
  },
  {
    "title": "T.Herremans"
  }
]
